sns_message_validator2/__init__.py
sns_message_validator2/exceptions.py
sns_message_validator2/sns_message_type.py
sns_message_validator2/sns_message_validator.py
aws_sns_message_validator2-0.0.1.dist-info/LICENSE
aws_sns_message_validator2-0.0.1.dist-info/WHEEL
aws_sns_message_validator2-0.0.1.dist-info/METADATA
aws_sns_message_validator2-0.0.1.dist-info/RECORD
